db_anonnymizer/__init__.py
db_anonnymizer/business.py
db_anonnymizer/dbal.py
db_anonnymizer-1.0.2.dist-info/METADATA
db_anonnymizer-1.0.2.dist-info/WHEEL
db_anonnymizer-1.0.2.dist-info/entry_points.txt
db_anonnymizer-1.0.2.dist-info/top_level.txt
db_anonnymizer-1.0.2.dist-info/RECORD
