Metadata-Version: 2.1
Name: db-anonnymizer
Version: 1.0.2
Summary: Database anonnymized tool
Home-page: UNKNOWN
Author: Omar Diaz
Author-email: omar.diaz@crosslend.com
License: UNKNOWN
Platform: UNKNOWN
Requires-Dist: Click
Requires-Dist: dsnparse
Requires-Dist: mysql-connector-python
Requires-Dist: pyyaml
Requires-Dist: Faker
